tela_client/__init__.py
tela_client/__version__.py
tela_client/client.py
tela_client/folder_watcher.py
tela_client/hooks.py
tela_client/utils.py
tela_client-0.4.6.dist-info/METADATA
tela_client-0.4.6.dist-info/WHEEL
tela_client-0.4.6.dist-info/top_level.txt
tela_client-0.4.6.dist-info/RECORD
