Metadata-Version: 2.4
Name: tela-client
Version: 0.4.6
Summary: A client library for interacting with the Tela API
Home-page: https://github.com/yourusername/tela-client
Author: Meistrari
Author-email: contato@meistrari.com
Classifier: Development Status :: 3 - Alpha
Classifier: Intended Audience :: Developers
Classifier: License :: OSI Approved :: MIT License
Classifier: Operating System :: OS Independent
Classifier: Programming Language :: Python :: 3
Classifier: Programming Language :: Python :: 3.7
Classifier: Programming Language :: Python :: 3.8
Classifier: Programming Language :: Python :: 3.9
Requires-Python: >=3.7
Requires-Dist: requests
Requires-Dist: pandas
Requires-Dist: watchdog
Dynamic: author
Dynamic: author-email
Dynamic: classifier
Dynamic: description
Dynamic: description-content-type
Dynamic: home-page
Dynamic: requires-dist
Dynamic: requires-python
Dynamic: summary
